[
{
      "_id": 1,
      "managementName": "Team Vitality",
      "description": "A Team Vitality egy francia esport szervezet, amelynek csapatai a Rocket League-ben versenyeznek.",
      "isEurope": true,
      "managementSize": 10,
      "location": "1",
      "creationDate": "2013-01-01",
      "pictureUrl": "http://elit.jedlik.eu/nits/RL/vitality.jpg"
    },
    {  
   "_id": 2,
      "teamName": "Dignitas",
      "description": "A Dignitas egy amerikai esport szervezet, jelenleg egy Európai Rocket League csapatot indít.",
      "isEurope": true,
      "managementSize": 10,
      "location": "2",
      "creationDate": "2003-09-01",
      "pictureUrl": "http://elit.jedlilk.eu/nits/RL/dignitas.jpg"
    },
    {  
      "_id": 3,
      "teamName": "Team BDS",
      "description": "A Team BDS egy svájci esport szervezet, amelynek székhelye Genfben található.",
      "isEurope": true,
      "managementSize": 10,
      "location": "3",
      "creationDate": "2019-01-01",
      "pictureUrl": "http://elit.jedlik.eu/nits/RL/team-bds.jpg"
    },
    {
      "_id": 4,
      "teamName": "Team Liquid",
      "description": "A Team Liquid egy multi-gaming team, amelyet 2000-ben alapítottak Hollandiában",
      "isEurope": true,
      "managementSize": 10,
      "location": "4",
      "creationDate": "2000-01-01",
      "pictureUrl": "http://elit.jedlik.eu/nits/RL/team-liquid.jpg"
    },
    {
      "_id": 5,
      "teamName": "Team Endpoint",
      "description": "A Team Endpoint egy 2016-ban alapított brit multi-gaming team.",
      "isEurope": true,
      "managementSize": 10,
      "location": "5",
      "creationDate": "2016-08-01",
      "pictureUrl": "http://elit.jedlik.eu/nits/RL/team-endpoint.jpg"
    },
    {
      "_id": 6,
      "teamName": "Solary",
      "description": "A Solary egy francia szervezet, amelynek székhelye Toursban található.",
      "isEurope": true,
      "managementSize": 8,
      "location": "6",
      "creationDate": "2017-01-01",
      "pictureUrl": "http://elit.jedlik.eu/nits/RL/solary.jpg"
    },
    {
      "_id": 7,
      "teamName": "Guild Esports",
      "description": "A Guild Esports PLC (korábban The Lords Esports) egy 2019-ben alapított, egyesült királyságbeli székhelyű professzionális esport cég.",
      "isEurope": true,
      "managementSize": 10,
      "location": "5",
      "creationDate": "2020-06-01",
      "pictureUrl": "http://elit.jedlik.eu/nits/RL/guild-esports.jpg"
    },
    {  
      "_id": 8,
      "teamName": "Oxygen",
      "description": "Az Oxygen Esports (rövidítve OXG) egy amerikai professzionális esport szervezet, amely jelenleg Új-Angliában található.",
      "isEurope": true,
      "managementSize": 9,
      "location": "2",
      "creationDate": "2020-01-01",
      "pictureUrl": "http://elit.jedlik.eu/nits/RL/oxygen-esports.jpg"
    },
    {
      "_id": 9,
      "teamName": "Alpine",
      "description": "A Torrent (korábbi nevén Alpine Esports) egy amerikai esport szervezet",
      "isEurope": false,
      "managementSize": 7,
      "location": "2",
      "creationDate": "2019-01-01",
      "pictureUrl": "http://elit.jedlik.eu/nits/RL/alpine.jpg"
    },
    {
      "_id": 10,
      "teamName": "Team envy",
      "description": "A Team Envy egy 2007-ben alapított amerikai esport szervezet",
      "isEurope": false,
      "managementSize": 10,
      "location": "2",
      "creationDate": "2019-01-01",
      "pictureUrl": "http://elit.jedlik.eu/nits/RL/envy.jpg"
    }
  ]
